plasgate/__init__.py
plasgate/api/__init__.py
plasgate/api/message.py
plasgate/api/schema.py
plasgate/rest/__init__.py
plasgate_sms-1.0.0.dist-info/METADATA
plasgate_sms-1.0.0.dist-info/WHEEL
plasgate_sms-1.0.0.dist-info/top_level.txt
plasgate_sms-1.0.0.dist-info/RECORD
